MANIFEST.in
README.rst
bootstrap-buildout.py
buildout.cfg
setup.cfg
setup.py
version.txt
antispoofing/__init__.py
antispoofing.motion.egg-info/PKG-INFO
antispoofing.motion.egg-info/SOURCES.txt
antispoofing.motion.egg-info/dependency_links.txt
antispoofing.motion.egg-info/entry_points.txt
antispoofing.motion.egg-info/requires.txt
antispoofing.motion.egg-info/top_level.txt
antispoofing.motion.egg-info/zip-safe
antispoofing/motion/__init__.py
antispoofing/motion/cluster.py
antispoofing/motion/framediff.py
antispoofing/motion/ml/__init__.py
antispoofing/motion/ml/perf.py
antispoofing/motion/ml/rprop.py
antispoofing/motion/ml/time.py
antispoofing/motion/script/__init__.py
antispoofing/motion/script/diffcluster.py
antispoofing/motion/script/framediff.py
antispoofing/motion/script/ldatrain.py
antispoofing/motion/script/make_scores.py
antispoofing/motion/script/merge_scores.py
antispoofing/motion/script/rproptrain.py
antispoofing/motion/script/time_analysis.py