Metadata-Version: 1.0
Name: antispoofing.motion
Version: 2.0.3
Summary: Motion counter-measures for the REPLAY-ATTACK database
Home-page: http://pypi.python.org/pypi/antispoofing.motion
Author: Andre Anjos
Author-email: andre.anjos@idiap.ch
License: GPLv3
Platform: UNKNOWN
